pysamss/LICENSE.txt
pysamss/__init__.py
pysamss/control/__init__.py
pysamss/control/pidcontroller.py
pysamss/forcetorque/__init__.py
pysamss/forcetorque/gravity.py
pysamss/forcetorque/thrust.py
pysamss/gui/__init__.py
pysamss/gui/mainwindow.py
pysamss/gui/mayavi_qwidget.py
pysamss/gui/postwindow.py
pysamss/helpermath/__init__.py
pysamss/helpermath/helpermath.py
pysamss/helpermath/orbital.py
pysamss/main/__init__.py
pysamss/main/celestialbody.py
pysamss/main/referenceframe.py
pysamss/main/rigidbody.py
pysamss/main/stage.py
pysamss/main/system.py
pysamss/main/timestep.py
pysamss/main/vessel.py
pysamss/plotting/__init__.py
pysamss/plotting/navball.py
pysamss/plotting/plotting.py
pysamss/resources/__init__.py
pysamss/resources/earth.jpg
pysamss/resources/mars.jpg
pysamss/resources/moon.jpg
pysamss/resources/navball_brownblue.jpg
pysamss/resources/starmap_celestial.jpg
pysamss/resources/starmap_galactic.jpg
pysamss/resources/sun.jpg
pysamss-0.0.2.dist-info/LICENSE.txt
pysamss-0.0.2.dist-info/METADATA
pysamss-0.0.2.dist-info/WHEEL
pysamss-0.0.2.dist-info/top_level.txt
pysamss-0.0.2.dist-info/RECORD
