Metadata-Version: 2.1
Name: pysamss
Version: 0.0.2
Summary: Python Space Asset Management and Simulation System
Home-page: https://github.com/c-bruce/pysamss
Author: Callum Bruce
Author-email: callum.bruce1@gmail.com
License: MIT License
Platform: UNKNOWN
Requires-Dist: h5py (>=2.10.0)
Requires-Dist: jplephem (>=2.14)
Requires-Dist: julian (>=0.14)
Requires-Dist: mayavi (>=4.7.1)
Requires-Dist: numpy (>=1.18.1)
Requires-Dist: PyQt5 (>=5.14.2)
Requires-Dist: pyquaternion (>=0.9.5)
Requires-Dist: sgp4 (>=2.7)
Requires-Dist: vtk (>=8.1.2)
